<configuration>
    <property>
        <name>dfs.replication</name>
        <value>1</value>
    </property>
    <property>
        <name>dfs.data.dir</name>
        <value>/tmp/hadoop-root/dfs/data_02</value>
    </property>
    <property>
        <name>dfs.datanode.address</name>
        <value>0.0.0.0:50011</value>
    </property>
    <property>
        <name>dfs.datanode.ipc.address</name>
        <value>0.0.0.0:50021</value>
    </property>
    <property>
        <name>dfs.datanode.http.address</name>
        <value>0.0.0.0:50076</value>
    </property>
    <property>
        <name>dfs.datanode.https.address</name>
        <value>0.0.0.0:50476</value>
    </property>
</configuration>
